include/b2nd.h
include/blosc2.h
include/blosc2/codecs-registry.h
include/blosc2/blosc2-stdio.h
include/blosc2/blosc2-common.h
include/blosc2/tuners-registry.h
include/blosc2/blosc2-export.h
include/blosc2/filters-registry.h
lib/libblosc2.2.22.1.dylib
lib/libblosc2.a
lib/libblosc2.6.dylib
lib/libblosc2.dylib
lib/pkgconfig/blosc2.pc
lib/cmake/Blosc2/Blosc2Targets-release.cmake
lib/cmake/Blosc2/Blosc2ConfigVersion.cmake
lib/cmake/Blosc2/Blosc2Targets.cmake
lib/cmake/Blosc2/Blosc2Config.cmake
lib/cmake/Blosc2/Modules/FindLZ4.cmake
lib/cmake/Blosc2/Modules/toolchain-armsf.cmake
lib/cmake/Blosc2/Modules/FindZSTD.cmake
lib/cmake/Blosc2/Modules/FindZLIB_NG.cmake
lib/cmake/Blosc2/Modules/FindIPP.cmake
lib/cmake/Blosc2/Modules/toolchain-armhf.cmake
lib/cmake/Blosc2/Modules/toolchain-aarch64.cmake
lib/cmake/Blosc2/Modules/FindSIMD.cmake
blosc2-3.12.1.dist-info/RECORD
blosc2-3.12.1.dist-info/WHEEL
blosc2-3.12.1.dist-info/entry_points.txt
blosc2-3.12.1.dist-info/METADATA
blosc2-3.12.1.dist-info/licenses/LICENSE.txt
blosc2/schunk.py
blosc2/blosc2_ext.pyx
blosc2/version.py
blosc2/tree_store.py
blosc2/lazyexpr.py
blosc2/blosc2_ext.cpython-314-darwin.so
blosc2/proxy.py
blosc2/c2array.py
blosc2/__init__.py
blosc2/core.py
blosc2/dict_store.py
blosc2/ndarray.py
blosc2/linalg.py
blosc2/utils.py
blosc2/storage.py
blosc2/embed_store.py
blosc2/exceptions.py
blosc2/fft.py
blosc2/info.py
