Metadata-Version: 2.2
Name: blosc2
Version: 3.12.1
Summary: A fast & compressed ndarray library with a flexible compute engine.
Author-Email: Blosc Development Team <blosc@blosc.org>
Maintainer-Email: Blosc Development Team <blosc@blosc.org>
License: BSD-3-Clause
Classifier: Development Status :: 6 - Mature
Classifier: Intended Audience :: Developers
Classifier: Intended Audience :: Information Technology
Classifier: Intended Audience :: Science/Research
Classifier: License :: OSI Approved :: BSD License
Classifier: Programming Language :: Python
Classifier: Topic :: Software Development :: Libraries :: Python Modules
Classifier: Operating System :: Microsoft :: Windows
Classifier: Operating System :: Unix
Classifier: Programming Language :: Python :: 3
Classifier: Programming Language :: Python :: 3.10
Classifier: Programming Language :: Python :: 3.11
Classifier: Programming Language :: Python :: 3.12
Classifier: Programming Language :: Python :: 3.13
Classifier: Programming Language :: Python :: 3.14
Project-URL: homepage, https://github.com/Blosc/python-blosc2
Project-URL: documentation, https://www.blosc.org/python-blosc2/python-blosc2.html
Requires-Python: >=3.10
Requires-Dist: numpy>=1.26
Requires-Dist: ndindex
Requires-Dist: msgpack
Requires-Dist: platformdirs
Requires-Dist: numexpr>=2.14.1; platform_machine != "wasm32"
Requires-Dist: py-cpuinfo; platform_machine != "wasm32"
Requires-Dist: requests
Provides-Extra: dev
Requires-Dist: dask; extra == "dev"
Requires-Dist: h5py; extra == "dev"
Requires-Dist: hdf5plugin; extra == "dev"
Requires-Dist: jupyterlab; extra == "dev"
Requires-Dist: matplotlib; extra == "dev"
Requires-Dist: pandas; extra == "dev"
Requires-Dist: plotly; extra == "dev"
Requires-Dist: pre-commit; extra == "dev"
Requires-Dist: pyarrow; extra == "dev"
Requires-Dist: ruff; extra == "dev"
Requires-Dist: s3fs; extra == "dev"
Requires-Dist: xarray; extra == "dev"
Requires-Dist: zarr; extra == "dev"
Provides-Extra: test
Requires-Dist: pytest; extra == "test"
Requires-Dist: psutil; platform_machine != "wasm32" and extra == "test"
Requires-Dist: torch; platform_machine != "wasm32" and extra == "test"
Provides-Extra: doc
Requires-Dist: sphinx>=8; extra == "doc"
Requires-Dist: pydata-sphinx-theme; extra == "doc"
Requires-Dist: numpydoc; extra == "doc"
Requires-Dist: myst-parser; extra == "doc"
Requires-Dist: sphinx-paramlinks; extra == "doc"
Requires-Dist: nbsphinx; extra == "doc"
Requires-Dist: ipykernel; extra == "doc"
Requires-Dist: sphinx-design; extra == "doc"
Requires-Dist: furo; extra == "doc"
Requires-Dist: numba; extra == "doc"
